aidge_learning/__init__.py
aidge_learning/aidge_learning.cpython-310-x86_64-linux-gnu.so
aidge_learning/version.txt
aidge_learning.libs/libgomp-a34b3233.so.1.0.0
aidge_learning-0.5.0.dist-info/RECORD
aidge_learning-0.5.0.dist-info/top_level.txt
aidge_learning-0.5.0.dist-info/METADATA
aidge_learning-0.5.0.dist-info/WHEEL
aidge_learning-0.5.0.dist-info/licenses/LICENSE
