Metadata-Version: 2.4
Name: aidge_learning
Version: 0.5.0
Summary: Functions and alogrithms to train models in the AIDGE framework
License: Eclipse Public License - v 2.0
Project-URL: Homepage, https://www.deepgreen.ai/en/platform
Project-URL: Documentation, https://eclipse.dev/aidge/
Project-URL: Repository, https://gitlab.eclipse.org/eclipse/aidge/aidge_learning
Project-URL: Issues, https://gitlab.eclipse.org/eclipse/aidge/aidge_learning/-/issues/
Project-URL: Changelog, https://gitlab.eclipse.org/eclipse/aidge/aidge_learning/-/releases
Classifier: Development Status :: 2 - Pre-Alpha
Classifier: Intended Audience :: Developers
Classifier: Intended Audience :: Education
Classifier: Intended Audience :: Science/Research
Classifier: License :: OSI Approved :: Eclipse Public License 2.0 (EPL-2.0)
Classifier: Programming Language :: C++
Classifier: Programming Language :: Python
Classifier: Programming Language :: Python :: 3
Classifier: Programming Language :: Python :: 3.10
Classifier: Programming Language :: Python :: 3.11
Classifier: Programming Language :: Python :: 3.12
Classifier: Programming Language :: Python :: 3.13
Classifier: Programming Language :: Python :: 3 :: Only
Classifier: Topic :: Scientific/Engineering
Classifier: Topic :: Scientific/Engineering :: Artificial Intelligence
Classifier: Topic :: Software Development
Requires-Python: >=3.10
License-File: LICENSE
Dynamic: license-file
